Metadata-Version: 2.1
Name: xscreensaver-config
Version: 1.0.7
Summary: Python parser for .xscreensaver config file
Home-page: https://github.com/Salamek/xscreensaver-config
Author: Adam Schubert
Author-email: adam.schubert@sg1-game.net
License: LGPL-3.0 
Project-URL: Release notes, https://github.com/Salamek/xscreensaver-config/releases
Platform: UNKNOWN
Classifier: Development Status :: 5 - Production/Stable
Classifier: Environment :: Console
Classifier: Intended Audience :: Developers
Classifier: License :: OSI Approved :: GNU Lesser General Public License v3 (LGPLv3)
Classifier: Operating System :: OS Independent
Classifier: Programming Language :: Python
Classifier: Programming Language :: Python :: 3
Classifier: Programming Language :: Python :: 3.4
Classifier: Programming Language :: Python :: 3.5
Classifier: Programming Language :: Python :: 3.6
Classifier: Programming Language :: Python :: 3.7
Classifier: Programming Language :: Python :: 3.8
Classifier: Topic :: Software Development
Requires-Python: >=3.4
